peoplequant/__init__.py
peoplequant/example.py
peoplequant/indicators.py
peoplequant/pqctp.py
peoplequant/zhuchannel.py
peoplequant/zhustruct.py
peoplequant/datastruct_error/6.7.11_API接口说明.chm
peoplequant/datastruct_error/ThostFtdcMdApi.h
peoplequant/datastruct_error/ThostFtdcTraderApi.h
peoplequant/datastruct_error/ThostFtdcUserApiDataType.h
peoplequant/datastruct_error/ThostFtdcUserApiStruct.h
peoplequant/datastruct_error/error.dtd
peoplequant/datastruct_error/error.xml
peoplequant/example/K线合成.py
peoplequant/example/example.py
peoplequant/example/example_demo.py
peoplequant/example/trade_template.html
peoplequant/example/交易统计_多线程.py
peoplequant/example/发邮箱_钉钉_多线程.py
peoplequant/example/多策略隔离_多线程.py
peoplequant/example/多线程示例.py
peoplequant/example/天勤信号结合.py
peoplequant/example/天勤结合.py
peoplequant/example/套利交易.py
peoplequant/example/套利对冲.py
peoplequant/example/常用指标计算.py
peoplequant/example/异步协程示例.py
peoplequant/example/播放音频_多线程.py
peoplequant/example/无人监控.py
peoplequant/example/智能调仓_协程.py
peoplequant/example/智能调仓_多线程.py
peoplequant/example/期权_多线程.py
peoplequant/example/移动止损.py
peoplequant/example/远程管理策略.py
peoplequant/libs/__init__.py
peoplequant/libs/_thostmduserapi.pyd
peoplequant/libs/_thosttraderapi.pyd
peoplequant/libs/ctpapi.cp314-win_amd64.pyd
peoplequant/libs/thostmduserapi.py
peoplequant/libs/thostmduserapi_se.dll
peoplequant/libs/thosttraderapi.py
peoplequant/libs/thosttraderapi_se.dll
peoplequant/穿透式认证/穿透式测试流程.docx
peoplequant/穿透式认证/穿透认证_交易指令检查.py
peoplequant/穿透式认证/穿透认证_基础交易功能.py
peoplequant/穿透式认证/穿透认证_应急处置暂停交易.py
peoplequant/穿透式认证/穿透认证_批量撤单.py
peoplequant/穿透式认证/穿透认证_报撤单笔数信息量等监测.py
peoplequant/穿透式认证/穿透认证_系统连接状态异常监测.py
peoplequant/穿透式认证/穿透认证_连通性.py
peoplequant/穿透式认证/穿透认证_重复报单监测.py
peoplequant/穿透式认证/穿透认证_错误防范.py
peoplequant/穿透式认证/穿透认证_阈值设置及预警.py
peoplequant-1.3.3.dist-info/METADATA
peoplequant-1.3.3.dist-info/WHEEL
peoplequant-1.3.3.dist-info/top_level.txt
peoplequant-1.3.3.dist-info/RECORD
