Metadata-Version: 2.4
Name: peoplequant
Version: 1.3.3
Summary: PeopleQuant trading CTP API package
Author: ZhuXueLi
Author-email: 3416223155@qq.com
License: Apache-2.0
Project-URL: Homepage, https://github.com/zhuxueli-cta/PeopleQuant
Project-URL: Source, http://118.89.87.140:8080/
Keywords: 穿透式认证,量化,ctp,openctp,quant,peoplequant
Classifier: Programming Language :: Python :: 3.12
Classifier: Programming Language :: Python :: 3.13
Classifier: Programming Language :: Python :: 3.14
Classifier: Operating System :: Microsoft :: Windows :: Windows 10
Classifier: Operating System :: Microsoft :: Windows :: Windows 11
Classifier: License :: OSI Approved :: Apache Software License
Requires-Dist: requests
Requires-Dist: polars
Requires-Dist: duckdb
Requires-Dist: pyarrow
Requires-Dist: numpy
Requires-Dist: pandas
Requires-Dist: openctp-ctp
